LICENSE
MANIFEST.in
README.md
setup.py
NGram/AdditiveSmoothing.c
NGram/AdditiveSmoothing.pyx
NGram/GoodTuringSmoothing.c
NGram/GoodTuringSmoothing.pxd
NGram/GoodTuringSmoothing.pyx
NGram/InterpolatedSmoothing.c
NGram/InterpolatedSmoothing.pyx
NGram/LaplaceSmoothing.c
NGram/LaplaceSmoothing.pxd
NGram/LaplaceSmoothing.pyx
NGram/MultipleFile.c
NGram/MultipleFile.pxd
NGram/MultipleFile.pyx
NGram/NGram.c
NGram/NGram.pxd
NGram/NGram.pyx
NGram/NGramNode.c
NGram/NGramNode.pxd
NGram/NGramNode.pyx
NGram/NoSmoothing.c
NGram/NoSmoothing.pxd
NGram/NoSmoothing.pyx
NGram/NoSmoothingWithDictionary.c
NGram/NoSmoothingWithDictionary.pyx
NGram/NoSmoothingWithNonRareWords.c
NGram/NoSmoothingWithNonRareWords.pyx
NGram/SimpleSmoothing.c
NGram/SimpleSmoothing.pxd
NGram/SimpleSmoothing.pyx
NGram/TrainedSmoothing.c
NGram/TrainedSmoothing.pxd
NGram/TrainedSmoothing.pyx
NGram/__init__.py
NlpToolkit_NGram_Cy.egg-info/PKG-INFO
NlpToolkit_NGram_Cy.egg-info/SOURCES.txt
NlpToolkit_NGram_Cy.egg-info/dependency_links.txt
NlpToolkit_NGram_Cy.egg-info/requires.txt
NlpToolkit_NGram_Cy.egg-info/top_level.txt
nlptoolkit_ngram_cy.egg-info/PKG-INFO
nlptoolkit_ngram_cy.egg-info/SOURCES.txt
nlptoolkit_ngram_cy.egg-info/dependency_links.txt
nlptoolkit_ngram_cy.egg-info/requires.txt
nlptoolkit_ngram_cy.egg-info/top_level.txt