Metadata-Version: 2.4
Name: nlptoolkit-ngram-cy
Version: 1.0.12
Summary: NGram library
Home-page: https://github.com/StarlangSoftware/NGram-Cy
Author: olcaytaner
Author-email: olcay.yildiz@ozyegin.edu.tr
License-File: LICENSE
Requires-Dist: NlpToolkit-DataStructure-Cy
Requires-Dist: NlpToolkit-Sampling-Cy
Dynamic: author
Dynamic: author-email
Dynamic: description
Dynamic: description-content-type
Dynamic: home-page
Dynamic: license-file
Dynamic: requires-dist
Dynamic: summary
